jupyterlab_mystjs/__init__.py
jupyterlab_mystjs/_version.py
jupyterlab_mystjs-0.1.4.data/data/share/jupyter/labextensions/jupyterlab-mystjs/package.json
jupyterlab_mystjs-0.1.4.data/data/share/jupyter/labextensions/jupyterlab-mystjs/static/00b26ac825e2095056396e0553b8ac26d3f8ad158c3826e28b4c45b385c4714a.woff2
jupyterlab_mystjs-0.1.4.data/data/share/jupyter/labextensions/jupyterlab-mystjs/static/07d8e303ce4fc12b4bb54f1004170dd190a1f3db45d400fe68060df3e0897268.ttf
jupyterlab_mystjs-0.1.4.data/data/share/jupyter/labextensions/jupyterlab-mystjs/static/08ce98e51b04d58945a301e639e02b6998af29fdfd61a7b8afdd07bbfc479d4a.ttf
jupyterlab_mystjs-0.1.4.data/data/share/jupyter/labextensions/jupyterlab-mystjs/static/0cdd387c9590a1a9f9794560022dbb59654a7d86f187aa0c81495ad42d3a7308.woff2
jupyterlab_mystjs-0.1.4.data/data/share/jupyter/labextensions/jupyterlab-mystjs/static/0d85ae7cc30f23790a7f1a58c4a112fdca8aae769b6ba11429af1d98b1b6cb3a.ttf
jupyterlab_mystjs-0.1.4.data/data/share/jupyter/labextensions/jupyterlab-mystjs/static/0f60d1b897938ec918c8ce073092411baf9438f6739465693ff18b0f9d20b021.woff2
jupyterlab_mystjs-0.1.4.data/data/share/jupyter/labextensions/jupyterlab-mystjs/static/112.719e19914375837b3fd7.js
jupyterlab_mystjs-0.1.4.data/data/share/jupyter/labextensions/jupyterlab-mystjs/static/112.719e19914375837b3fd7.js.LICENSE.txt
jupyterlab_mystjs-0.1.4.data/data/share/jupyter/labextensions/jupyterlab-mystjs/static/11e4dc8a6471ff6d6ee561d53d10fde8f7489e798257ff449c5d37c197435605.woff
jupyterlab_mystjs-0.1.4.data/data/share/jupyter/labextensions/jupyterlab-mystjs/static/138ac28d1663b3037e9c5f52371fa5c63d8324f4a38d22cd573e6ea3a3fd0cf8.ttf
jupyterlab_mystjs-0.1.4.data/data/share/jupyter/labextensions/jupyterlab-mystjs/static/156.a7ef97f9ccc27a68df81.js
jupyterlab_mystjs-0.1.4.data/data/share/jupyter/labextensions/jupyterlab-mystjs/static/156.a7ef97f9ccc27a68df81.js.LICENSE.txt
jupyterlab_mystjs-0.1.4.dist-info/METADATA
jupyterlab_mystjs-0.1.4.dist-info/WHEEL
jupyterlab_mystjs-0.1.4.dist-info/licenses/LICENSE
jupyterlab_mystjs-0.1.4.dist-info/RECORD
